README.md
setup.py
kurve/__init__.py
kurve/base_source.py
kurve/cardinality.py
kurve/edge_builder.py
kurve/entity.py
kurve/enums.py
kurve/graph.py
kurve/middleware.py
kurve/sources.py
kurve/util.py
kurve.egg-info/PKG-INFO
kurve.egg-info/SOURCES.txt
kurve.egg-info/dependency_links.txt
kurve.egg-info/not-zip-safe
kurve.egg-info/requires.txt
kurve.egg-info/top_level.txt
kurve/models/__init__.py
tests/test_bigquery_graph.py
tests/test_local_graph.py
tests/test_postgres_graph.py
tests/test_s3_graph.py