Metadata-Version: 2.1
Name: kurve
Version: 0.3
Summary: An interface for dynamic entity linking with graphs as the backend for arbitrary data sources.
Home-page: https://github.com/kurveai/kurve
Author: Wes Madrigal
Author-email: wes@madconsulting.ai
License: MIT
Project-URL: Source, http://github.com/kurveai/kurve
Project-URL: Issue Tracker, https://github.com/kurveai/kurve/issues
Keywords: knowledge discovery,data discovery,data visualization,entity linking,graph algorithms,knowledge graph,parsing
Classifier: Programming Language :: Python :: 3
Classifier: License :: OSI Approved :: MIT License
Classifier: Operating System :: OS Independent
Classifier: Development Status :: 5 - Production/Stable
Classifier: Intended Audience :: Developers
Classifier: Intended Audience :: Education
Classifier: Intended Audience :: Information Technology
Classifier: Intended Audience :: Science/Research
Classifier: Topic :: Scientific/Engineering :: Information Analysis
Provides-Extra: base
